behance_python3/__init__.py
behance_python3/api.py
behance_python3/behance.py
behance_python3/collection.py
behance_python3/exceptions.py
behance_python3/project.py
behance_python3/user.py
behance_python3/wip.py
behance_python3-0.3.2.dist-info/METADATA
behance_python3-0.3.2.dist-info/RECORD
behance_python3-0.3.2.dist-info/WHEEL
behance_python3-0.3.2.dist-info/top_level.txt
