Metadata-Version: 2.1
Name: behance-python3
Version: 0.3.2
Summary: UNKNOWN
Home-page: https://github.com/Menda0/behance_python3
Author: Alex Ravenel
Author-email: ravenel@gmail.com
License: MIT
Platform: UNKNOWN
Requires-Dist: requests
